Denzven_Graphing_Api_Wrapper/__init__.py
Denzven_Graphing_Api_Wrapper-0.0.0.5.dist-info/METADATA
Denzven_Graphing_Api_Wrapper-0.0.0.5.dist-info/WHEEL
Denzven_Graphing_Api_Wrapper-0.0.0.5.dist-info/top_level.txt
Denzven_Graphing_Api_Wrapper-0.0.0.5.dist-info/RECORD
