Metadata-Version: 2.1
Name: Denzven_Graphing_Api_Wrapper
Version: 0.0.0.5
Summary: An Api Wrapper for the Denzven-Graphing-Api
Home-page: https://denzven.pythonanywhere.com
Author: Denzven
Author-email: denzvenvadakkan@gmail.com
License: UNKNOWN
Project-URL: Bug Tracker, https://github.com/denzven/Denzven-Graphing-Api-Wrapper/issues
Project-URL: Documentation, https://denzgraphingapiwrapper-py.readthedocs.io/en/latest/
Project-URL: Source, https://github.com/denzven/Denzven-Graphing-Api-Wrapper
Platform: UNKNOWN
Classifier: Programming Language :: Python :: 3
Classifier: License :: OSI Approved :: MIT License
Classifier: Operating System :: OS Independent
Requires-Python: >=3.6
